FreeFireGETinfo/__init__.py
FreeFireGETinfo/main.py
FreeFireGETinfo-0.1.4.dist-info/METADATA
FreeFireGETinfo-0.1.4.dist-info/WHEEL
FreeFireGETinfo-0.1.4.dist-info/entry_points.txt
FreeFireGETinfo-0.1.4.dist-info/top_level.txt
FreeFireGETinfo-0.1.4.dist-info/RECORD
