Metadata-Version: 2.1
Name: FreeFireGETinfo
Version: 0.1.4
Requires-Dist: requests ==2.31.0
